cq_cli/__init__.py
cq_cli/main.py
cq_cli/cqcodecs/__init__.py
cq_cli/cqcodecs/codec_helpers.py
cq_cli/cqcodecs/cq_codec_dxf.py
cq_cli/cqcodecs/cq_codec_glb.py
cq_cli/cqcodecs/cq_codec_gltf.py
cq_cli/cqcodecs/cq_codec_step.py
cq_cli/cqcodecs/cq_codec_stl.py
cq_cli/cqcodecs/cq_codec_svg.py
cq_cli/cqcodecs/cq_codec_threejs.py
cq_cli/cqcodecs/loader.py
cadquery_cli-2.3.0.dist-info/METADATA
cadquery_cli-2.3.0.dist-info/WHEEL
cadquery_cli-2.3.0.dist-info/entry_points.txt
cadquery_cli-2.3.0.dist-info/licenses/LICENSE
cadquery_cli-2.3.0.dist-info/RECORD
