Metadata-Version: 2.4
Name: cadquery-cli
Version: 2.3.0
Summary: Command Line Interface for executing CadQuery scripts and converting their output to another format.
Project-URL: Homepage, https://github.com/CadQuery/cq-cli
Project-URL: Bug Tracker, https://github.com/CadQuery/cq-cli/issues
Author: Jeremy Wright
License:                                  Apache License
License-File: LICENSE
Classifier: Operating System :: OS Independent
Classifier: Programming Language :: Python :: 3
Requires-Python: >=3.9
Requires-Dist: cadquery
Requires-Dist: cadquery-freecad-import-plugin
Provides-Extra: dev
Requires-Dist: black==19.10b0; extra == 'dev'
Requires-Dist: click==8.0.4; extra == 'dev'
Requires-Dist: pytest; extra == 'dev'
